LICENSE.md
README.md
setup.cfg
setup.py
rftokenizer/__init__.py
rftokenizer/conllu2segs.py
rftokenizer/f_score_segs.py
rftokenizer/flair_pos_tagger.py
rftokenizer/timing.py
rftokenizer/tokenize_rf.py
rftokenizer.egg-info/PKG-INFO
rftokenizer.egg-info/SOURCES.txt
rftokenizer.egg-info/dependency_links.txt
rftokenizer.egg-info/requires.txt
rftokenizer.egg-info/top_level.txt
rftokenizer/data/SPMRL_dev_gold.tab
rftokenizer/data/SPMRL_dev_plain.tab
rftokenizer/data/SPMRL_test_gold.tab
rftokenizer/data/SPMRL_test_plain.tab
rftokenizer/data/SPMRL_train_gold.tab
rftokenizer/data/SPMRL_train_plain.tab
rftokenizer/data/Wiki5K_test_gold.tab
rftokenizer/data/Wiki5K_test_plain.tab
rftokenizer/data/ara.conf
rftokenizer/data/ara.frq
rftokenizer/data/ara.lex
rftokenizer/data/ara_dev.tab
rftokenizer/data/ara_dev_plain.tab
rftokenizer/data/ara_dev_train.tab
rftokenizer/data/ara_test.tab
rftokenizer/data/ara_test_plain.tab
rftokenizer/data/ara_train.tab
rftokenizer/data/ara_train_plain.tab
rftokenizer/data/boh.conf
rftokenizer/data/boh.lex
rftokenizer/data/boh_train.tab
rftokenizer/data/cop.conf
rftokenizer/data/cop.frq
rftokenizer/data/cop.lex
rftokenizer/data/cop_dev.tab
rftokenizer/data/cop_dev_plain.tab
rftokenizer/data/cop_test.tab
rftokenizer/data/cop_test_plain.tab
rftokenizer/data/cop_train.tab
rftokenizer/data/cop_train_plain.tab
rftokenizer/data/eng.conf
rftokenizer/data/eng.frq
rftokenizer/data/eng.lex
rftokenizer/data/eng_big.frq
rftokenizer/data/eng_dev.tab
rftokenizer/data/eng_dev_plain.tab
rftokenizer/data/eng_dev_pred.tab
rftokenizer/data/eng_dev_sents.tab
rftokenizer/data/eng_dev_stanza.tab
rftokenizer/data/eng_dev_stanza_ewt.tab
rftokenizer/data/eng_test.tab
rftokenizer/data/eng_test_plain.tab
rftokenizer/data/eng_test_pred.tab
rftokenizer/data/eng_test_sents.tab
rftokenizer/data/eng_test_stanza.tab
rftokenizer/data/eng_test_stanza_ewt.tab
rftokenizer/data/eng_train.tab
rftokenizer/data/eng_train_plain.tab
rftokenizer/data/eng_train_sents.tab
rftokenizer/data/gum_seg_data.zip
rftokenizer/data/gum_train_plain.tab
rftokenizer/data/he_iahltknesset-ud-dev.tab
rftokenizer/data/he_iahltknesset-ud-test.tab
